opentoolflux/__init__.py
opentoolflux/cli.py
opentoolflux/database.py
opentoolflux/fluxes.py
opentoolflux/logging_config.py
opentoolflux/measurements.py
opentoolflux/plot.py
opentoolflux/resources/__init__.py
opentoolflux/resources/matplotlib-style
opentoolflux-0.3.0.dist-info/LICENSE
opentoolflux-0.3.0.dist-info/METADATA
opentoolflux-0.3.0.dist-info/WHEEL
opentoolflux-0.3.0.dist-info/entry_points.txt
opentoolflux-0.3.0.dist-info/top_level.txt
opentoolflux-0.3.0.dist-info/RECORD
