Metadata-Version: 2.1
Name: opentoolflux
Version: 0.3.0
Summary: OpenToolFlux is a command-line application to estimate gas fluxes from automatic chamber data.
Home-page: https://github.com/rasmuse/opentoolflux
Author: Rasmus Einarsson, Carmen Galea, Alba Monistrol
Author-email: python-opentoolflux@rasmuseinarsson.se
Maintainer: Rasmus Einarsson
Maintainer-email: python-opentoolflux@rasmuseinarsson.se
License: MIT License
Classifier: Development Status :: 4 - Beta
Classifier: Intended Audience :: Science/Research
Classifier: Programming Language :: Python
Classifier: Programming Language :: Python :: 3
Classifier: Programming Language :: Python :: 3.8
Classifier: Programming Language :: Python :: 3.9
Classifier: Programming Language :: Python :: 3.10
Classifier: Programming Language :: Python :: 3.11
Classifier: Topic :: Scientific/Engineering
Requires-Python: >=3.8
License-File: LICENSE
Requires-Dist: click >=8.0
Requires-Dist: pandas >=1.4.0
Requires-Dist: pyarrow >=8.0
Requires-Dist: pydantic <2,>=1.9
Requires-Dist: tomli >=2.0.1
Requires-Dist: matplotlib >=3.5
